mat_ret/__init__.py
mat_ret/api.py
mat_ret/databases.py
mat_ret/property_mapping.py
mat_ret-0.1.0.dist-info/licenses/LICENSE
mat_ret-0.1.0.dist-info/METADATA
mat_ret-0.1.0.dist-info/WHEEL
mat_ret-0.1.0.dist-info/top_level.txt
mat_ret-0.1.0.dist-info/RECORD
