Metadata-Version: 2.4
Name: mat_ret
Version: 0.1.0
Summary: Unified retrieval and property mapping for materials databases (Materials Project, JARVIS, AFLOW, Alexandria, Materials Cloud, MPDS)
Author-email: Aadhityan A <aadhityan1995@gmail.com>
License: CeCILL FREE SOFTWARE LICENSE AGREEMENT
Project-URL: Homepage, https://github.com/Aadhityan-A/mat_ret
Project-URL: BugTracker, https://github.com/Aadhityan-A/mat_ret/issues
Requires-Python: >=3.8
License-File: LICENSE
Requires-Dist: pymatgen
Requires-Dist: requests
Requires-Dist: numpy
Requires-Dist: scipy
Requires-Dist: mp-api
Requires-Dist: jarvis-tools
Requires-Dist: optimade[http_client]
Requires-Dist: ase
Requires-Dist: aflow
Requires-Dist: matplotlib
Requires-Dist: pandas
Requires-Dist: tqdm
Requires-Dist: urllib3
Requires-Dist: mpds-client
Dynamic: license-file
